LICENSE.md
README.md
note.md
play.py
requirements.txt
setup.cfg
setup.py
.idea/vcs.xml
.idea/workspace.xml
dist/dsmlbc6_ebruagbay-0.0.1.tar.gz
dsmlbc6_ebruagbay/__init__.py
dsmlbc6_ebruagbay/hi.py
dsmlbc6_ebruagbay.egg-info/PKG-INFO
dsmlbc6_ebruagbay.egg-info/SOURCES.txt
dsmlbc6_ebruagbay.egg-info/dependency_links.txt
dsmlbc6_ebruagbay.egg-info/top_level.txt
dsmlbc6_ebruagbay/data_prep/__init__.py
dsmlbc6_ebruagbay/data_prep/data_prep.py
dsmlbc6_ebruagbay/eda/__init__.py
dsmlbc6_ebruagbay/eda/eda.py